mailshake/__init__.py
mailshake/message.py
mailshake/utils.py
mailshake/version.py
mailshake/mailers/__init__.py
mailshake/mailers/amazon_ses.py
mailshake/mailers/base.py
mailshake/mailers/console.py
mailshake/mailers/dummy.py
mailshake/mailers/filebased.py
mailshake/mailers/memory.py
mailshake/mailers/smtp.py
mailshake-2.3.dist-info/LICENSE
mailshake-2.3.dist-info/METADATA
mailshake-2.3.dist-info/WHEEL
mailshake-2.3.dist-info/top_level.txt
mailshake-2.3.dist-info/RECORD
