Metadata-Version: 2.1
Name: mailshake
Version: 2.3
Summary: Dramatically simplify sending email from your python app.
Home-page: https://github.com/jpsca/mailshake
Author: Juan-Pablo Scaletti
Author-email: juanpablo@jpscaletti.com
License: Apache License Version 2.0
Project-URL: Issue tracker, https://github.com/jpsca/mailshake/issues
Classifier: Development Status :: 5 - Production/Stable
Classifier: Intended Audience :: Developers
Classifier: License :: OSI Approved :: Apache Software License
Requires-Python: <4.0,>=3.6
License-File: LICENSE
Requires-Dist: html2text
Provides-Extra: dev
Requires-Dist: black ; extra == 'dev'
Requires-Dist: flake8 ; extra == 'dev'
Requires-Dist: pytest ; extra == 'dev'
Requires-Dist: pytest-cov ; extra == 'dev'
Requires-Dist: tox ; extra == 'dev'
Provides-Extra: test
Requires-Dist: flake8 ; extra == 'test'
Requires-Dist: pytest ; extra == 'test'
Requires-Dist: pytest-cov ; extra == 'test'
Requires-Dist: smtpdfix ; extra == 'test'
